README.md
setup.cfg
setup.py
keris/container.py
keris/initializers.py
keris/losses.py
keris/model.py
keris/trainer.py
keris.egg-info/PKG-INFO
keris.egg-info/SOURCES.txt
keris.egg-info/dependency_links.txt
keris.egg-info/requires.txt
keris.egg-info/top_level.txt
keris/utils/im2col.c