Metadata-Version: 1.1
Name: keris
Version: 0.3
Summary: Simple keras-like deep learning framework built with numpy
Home-page: https://github.com/arrizalamin/keris
Author: Arrizal Amin
Author-email: arrizalamin@gmail.com
License: MIT
Download-URL: https://github.com/arrizalamin/keris/archive/0.3.tar.gz
Keywords: deep learning,keris
Platform: UNKNOWN
